target_typo_proxy/__init__.py
target_typo_proxy/typo.py
test/__init__.py
test/test.py
target_typo_proxy-0.1.0.dist-info/LICENSE
target_typo_proxy-0.1.0.dist-info/METADATA
target_typo_proxy-0.1.0.dist-info/WHEEL
target_typo_proxy-0.1.0.dist-info/entry_points.txt
target_typo_proxy-0.1.0.dist-info/top_level.txt
target_typo_proxy-0.1.0.dist-info/RECORD
